{
  "headers": [
    "LProp3d_CLProps.hxx", 
    "LProp3d_SLProps.hxx", 
    "LProp3d_SurfaceTool.hxx", 
    "LProp3d_CurveTool.hxx"
  ], 
  "declarations": [
    {
      "declType": "class", 
      "name": "LProp3d_CurveTool", 
      "abstract": false, 
      "declarations": [
        {
          "declType": "method", 
          "name": "LProp3d_CurveTool", 
          "parent": "LProp3d_CurveTool", 
          "arguments": [], 
          "key": "LProp3d_CurveTool::LProp3d_CurveTool()", 
          "returnType": "", 
          "artificial": "1", 
          "throws": true, 
          "type": "constructor"
        }, 
        {
          "declType": "method", 
          "name": "LProp3d_CurveTool", 
          "parent": "LProp3d_CurveTool", 
          "arguments": [
            {
              "type": "LProp3d_CurveTool", 
              "name": "arg0", 
              "const": true, 
              "ref": true
            }
          ], 
          "key": "LProp3d_CurveTool::LProp3d_CurveTool(LProp3d_CurveTool)", 
          "returnType": "", 
          "artificial": "1", 
          "throws": true, 
          "type": "constructor", 
          "copyConstructor": true
        }, 
        {
          "declType": "method", 
          "name": "Value", 
          "parent": "LProp3d_CurveTool", 
          "arguments": [
            {
              "type": "opencascade::handle<Adaptor3d_HCurve>", 
              "name": "C", 
              "const": true, 
              "ref": true
            }, 
            {
              "type": "Standard_Real", 
              "name": "U", 
              "const": true
            }, 
            {
              "type": "gp_Pnt", 
              "name": "P", 
              "ref": true
            }
          ], 
          "key": "LProp3d_CurveTool::Value(opencascade::handle<Adaptor3d_HCurve>, Standard_Real, gp_Pnt)", 
          "returnType": "void", 
          "static": "1", 
          "throws": true
        }, 
        {
          "declType": "method", 
          "name": "D1", 
          "parent": "LProp3d_CurveTool", 
          "arguments": [
            {
              "type": "opencascade::handle<Adaptor3d_HCurve>", 
              "name": "C", 
              "const": true, 
              "ref": true
            }, 
            {
              "type": "Standard_Real", 
              "name": "U", 
              "const": true
            }, 
            {
              "type": "gp_Pnt", 
              "name": "P", 
              "ref": true
            }, 
            {
              "type": "gp_Vec", 
              "name": "V1", 
              "ref": true
            }
          ], 
          "key": "LProp3d_CurveTool::D1(opencascade::handle<Adaptor3d_HCurve>, Standard_Real, gp_Pnt, gp_Vec)", 
          "returnType": "void", 
          "static": "1", 
          "throws": true
        }, 
        {
          "declType": "method", 
          "name": "D2", 
          "parent": "LProp3d_CurveTool", 
          "arguments": [
            {
              "type": "opencascade::handle<Adaptor3d_HCurve>", 
              "name": "C", 
              "const": true, 
              "ref": true
            }, 
            {
              "type": "Standard_Real", 
              "name": "U", 
              "const": true
            }, 
            {
              "type": "gp_Pnt", 
              "name": "P", 
              "ref": true
            }, 
            {
              "type": "gp_Vec", 
              "name": "V1", 
              "ref": true
            }, 
            {
              "type": "gp_Vec", 
              "name": "V2", 
              "ref": true
            }
          ], 
          "key": "LProp3d_CurveTool::D2(opencascade::handle<Adaptor3d_HCurve>, Standard_Real, gp_Pnt, gp_Vec, gp_Vec)", 
          "returnType": "void", 
          "static": "1", 
          "throws": true
        }, 
        {
          "declType": "method", 
          "name": "D3", 
          "parent": "LProp3d_CurveTool", 
          "arguments": [
            {
              "type": "opencascade::handle<Adaptor3d_HCurve>", 
              "name": "C", 
              "const": true, 
              "ref": true
            }, 
            {
              "type": "Standard_Real", 
              "name": "U", 
              "const": true
            }, 
            {
              "type": "gp_Pnt", 
              "name": "P", 
              "ref": true
            }, 
            {
              "type": "gp_Vec", 
              "name": "V1", 
              "ref": true
            }, 
            {
              "type": "gp_Vec", 
              "name": "V2", 
              "ref": true
            }, 
            {
              "type": "gp_Vec", 
              "name": "V3", 
              "ref": true
            }
          ], 
          "key": "LProp3d_CurveTool::D3(opencascade::handle<Adaptor3d_HCurve>, Standard_Real, gp_Pnt, gp_Vec, gp_Vec, gp_Vec)", 
          "returnType": "void", 
          "static": "1", 
          "throws": true
        }, 
        {
          "declType": "method", 
          "name": "Continuity", 
          "parent": "LProp3d_CurveTool", 
          "arguments": [
            {
              "type": "opencascade::handle<Adaptor3d_HCurve>", 
              "name": "C", 
              "const": true, 
              "ref": true
            }
          ], 
          "key": "LProp3d_CurveTool::Continuity(opencascade::handle<Adaptor3d_HCurve>)", 
          "returnType": "Standard_Integer", 
          "static": "1", 
          "throws": true
        }, 
        {
          "declType": "method", 
          "name": "FirstParameter", 
          "parent": "LProp3d_CurveTool", 
          "arguments": [
            {
              "type": "opencascade::handle<Adaptor3d_HCurve>", 
              "name": "C", 
              "const": true, 
              "ref": true
            }
          ], 
          "key": "LProp3d_CurveTool::FirstParameter(opencascade::handle<Adaptor3d_HCurve>)", 
          "returnType": "Standard_Real", 
          "static": "1", 
          "throws": true
        }, 
        {
          "declType": "method", 
          "name": "LastParameter", 
          "parent": "LProp3d_CurveTool", 
          "arguments": [
            {
              "type": "opencascade::handle<Adaptor3d_HCurve>", 
              "name": "C", 
              "const": true, 
              "ref": true
            }
          ], 
          "key": "LProp3d_CurveTool::LastParameter(opencascade::handle<Adaptor3d_HCurve>)", 
          "returnType": "Standard_Real", 
          "static": "1", 
          "throws": true
        }
      ], 
      "artificial": false, 
      "bases": [], 
      "location": [
        "/usr/local/include/opencascade/LProp3d_CurveTool.hxx", 
        31
      ], 
      "key": "LProp3d_CurveTool"
    }, 
    {
      "declType": "class", 
      "name": "LProp3d_CLProps", 
      "abstract": false, 
      "declarations": [
        {
          "declType": "method", 
          "name": "LProp3d_CLProps", 
          "parent": "LProp3d_CLProps", 
          "arguments": [
            {
              "type": "opencascade::handle<Adaptor3d_HCurve>", 
              "name": "C", 
              "const": true, 
              "ref": true
            }, 
            {
              "type": "Standard_Integer", 
              "name": "N", 
              "const": true
            }, 
            {
              "type": "Standard_Real", 
              "name": "Resolution", 
              "const": true
            }
          ], 
          "key": "LProp3d_CLProps::LProp3d_CLProps(opencascade::handle<Adaptor3d_HCurve>, Standard_Integer, Standard_Real)", 
          "returnType": "", 
          "throws": true, 
          "type": "constructor"
        }, 
        {
          "declType": "method", 
          "name": "LProp3d_CLProps", 
          "parent": "LProp3d_CLProps", 
          "arguments": [
            {
              "type": "opencascade::handle<Adaptor3d_HCurve>", 
              "name": "C", 
              "const": true, 
              "ref": true
            }, 
            {
              "type": "Standard_Real", 
              "name": "U", 
              "const": true
            }, 
            {
              "type": "Standard_Integer", 
              "name": "N", 
              "const": true
            }, 
            {
              "type": "Standard_Real", 
              "name": "Resolution", 
              "const": true
            }
          ], 
          "key": "LProp3d_CLProps::LProp3d_CLProps(opencascade::handle<Adaptor3d_HCurve>, Standard_Real, Standard_Integer, Standard_Real)", 
          "returnType": "", 
          "throws": true, 
          "type": "constructor"
        }, 
        {
          "declType": "method", 
          "name": "LProp3d_CLProps", 
          "parent": "LProp3d_CLProps", 
          "arguments": [
            {
              "type": "Standard_Integer", 
              "name": "N", 
              "const": true
            }, 
            {
              "type": "Standard_Real", 
              "name": "Resolution", 
              "const": true
            }
          ], 
          "key": "LProp3d_CLProps::LProp3d_CLProps(Standard_Integer, Standard_Real)", 
          "returnType": "", 
          "throws": true, 
          "type": "constructor"
        }, 
        {
          "declType": "method", 
          "name": "LProp3d_CLProps", 
          "parent": "LProp3d_CLProps", 
          "arguments": [
            {
              "type": "LProp3d_CLProps", 
              "name": "arg0", 
              "const": true, 
              "ref": true
            }
          ], 
          "key": "LProp3d_CLProps::LProp3d_CLProps(LProp3d_CLProps)", 
          "returnType": "", 
          "artificial": "1", 
          "throws": true, 
          "type": "constructor", 
          "copyConstructor": true
        }, 
        {
          "declType": "method", 
          "name": "SetParameter", 
          "parent": "LProp3d_CLProps", 
          "arguments": [
            {
              "type": "Standard_Real", 
              "name": "U", 
              "const": true
            }
          ], 
          "key": "LProp3d_CLProps::SetParameter(Standard_Real)", 
          "returnType": "void", 
          "throws": true
        }, 
        {
          "declType": "method", 
          "name": "SetCurve", 
          "parent": "LProp3d_CLProps", 
          "arguments": [
            {
              "type": "opencascade::handle<Adaptor3d_HCurve>", 
              "name": "C", 
              "const": true, 
              "ref": true
            }
          ], 
          "key": "LProp3d_CLProps::SetCurve(opencascade::handle<Adaptor3d_HCurve>)", 
          "returnType": "void", 
          "throws": true
        }, 
        {
          "declType": "method", 
          "name": "Value", 
          "parent": "LProp3d_CLProps", 
          "arguments": [], 
          "key": "LProp3d_CLProps::Value()", 
          "returnType": "gp_Pnt const &", 
          "const": "1", 
          "throws": true
        }, 
        {
          "declType": "method", 
          "name": "D1", 
          "parent": "LProp3d_CLProps", 
          "arguments": [], 
          "key": "LProp3d_CLProps::D1()", 
          "returnType": "gp_Vec const &", 
          "throws": true
        }, 
        {
          "declType": "method", 
          "name": "D2", 
          "parent": "LProp3d_CLProps", 
          "arguments": [], 
          "key": "LProp3d_CLProps::D2()", 
          "returnType": "gp_Vec const &", 
          "throws": true
        }, 
        {
          "declType": "method", 
          "name": "D3", 
          "parent": "LProp3d_CLProps", 
          "arguments": [], 
          "key": "LProp3d_CLProps::D3()", 
          "returnType": "gp_Vec const &", 
          "throws": true
        }, 
        {
          "declType": "method", 
          "name": "IsTangentDefined", 
          "parent": "LProp3d_CLProps", 
          "arguments": [], 
          "key": "LProp3d_CLProps::IsTangentDefined()", 
          "returnType": "Standard_Boolean", 
          "throws": true
        }, 
        {
          "declType": "method", 
          "name": "Tangent", 
          "parent": "LProp3d_CLProps", 
          "arguments": [
            {
              "type": "gp_Dir", 
              "name": "D", 
              "ref": true
            }
          ], 
          "key": "LProp3d_CLProps::Tangent(gp_Dir)", 
          "returnType": "void", 
          "throws": true
        }, 
        {
          "declType": "method", 
          "name": "Curvature", 
          "parent": "LProp3d_CLProps", 
          "arguments": [], 
          "key": "LProp3d_CLProps::Curvature()", 
          "returnType": "Standard_Real", 
          "throws": true
        }, 
        {
          "declType": "method", 
          "name": "Normal", 
          "parent": "LProp3d_CLProps", 
          "arguments": [
            {
              "type": "gp_Dir", 
              "name": "N", 
              "ref": true
            }
          ], 
          "key": "LProp3d_CLProps::Normal(gp_Dir)", 
          "returnType": "void", 
          "throws": true
        }, 
        {
          "declType": "method", 
          "name": "CentreOfCurvature", 
          "parent": "LProp3d_CLProps", 
          "arguments": [
            {
              "type": "gp_Pnt", 
              "name": "P", 
              "ref": true
            }
          ], 
          "key": "LProp3d_CLProps::CentreOfCurvature(gp_Pnt)", 
          "returnType": "void", 
          "throws": true
        }
      ], 
      "artificial": false, 
      "bases": [], 
      "location": [
        "/usr/local/include/opencascade/LProp3d_CLProps.hxx", 
        42
      ], 
      "key": "LProp3d_CLProps"
    }, 
    {
      "declType": "class", 
      "name": "LProp3d_SurfaceTool", 
      "abstract": false, 
      "declarations": [
        {
          "declType": "method", 
          "name": "LProp3d_SurfaceTool", 
          "parent": "LProp3d_SurfaceTool", 
          "arguments": [], 
          "key": "LProp3d_SurfaceTool::LProp3d_SurfaceTool()", 
          "returnType": "", 
          "artificial": "1", 
          "throws": true, 
          "type": "constructor"
        }, 
        {
          "declType": "method", 
          "name": "LProp3d_SurfaceTool", 
          "parent": "LProp3d_SurfaceTool", 
          "arguments": [
            {
              "type": "LProp3d_SurfaceTool", 
              "name": "arg0", 
              "const": true, 
              "ref": true
            }
          ], 
          "key": "LProp3d_SurfaceTool::LProp3d_SurfaceTool(LProp3d_SurfaceTool)", 
          "returnType": "", 
          "artificial": "1", 
          "throws": true, 
          "type": "constructor", 
          "copyConstructor": true
        }, 
        {
          "declType": "method", 
          "name": "Value", 
          "parent": "LProp3d_SurfaceTool", 
          "arguments": [
            {
              "type": "opencascade::handle<Adaptor3d_HSurface>", 
              "name": "S", 
              "const": true, 
              "ref": true
            }, 
            {
              "type": "Standard_Real", 
              "name": "U", 
              "const": true
            }, 
            {
              "type": "Standard_Real", 
              "name": "V", 
              "const": true
            }, 
            {
              "type": "gp_Pnt", 
              "name": "P", 
              "ref": true
            }
          ], 
          "key": "LProp3d_SurfaceTool::Value(opencascade::handle<Adaptor3d_HSurface>, Standard_Real, Standard_Real, gp_Pnt)", 
          "returnType": "void", 
          "static": "1", 
          "throws": true
        }, 
        {
          "declType": "method", 
          "name": "D1", 
          "parent": "LProp3d_SurfaceTool", 
          "arguments": [
            {
              "type": "opencascade::handle<Adaptor3d_HSurface>", 
              "name": "S", 
              "const": true, 
              "ref": true
            }, 
            {
              "type": "Standard_Real", 
              "name": "U", 
              "const": true
            }, 
            {
              "type": "Standard_Real", 
              "name": "V", 
              "const": true
            }, 
            {
              "type": "gp_Pnt", 
              "name": "P", 
              "ref": true
            }, 
            {
              "type": "gp_Vec", 
              "name": "D1U", 
              "ref": true
            }, 
            {
              "type": "gp_Vec", 
              "name": "D1V", 
              "ref": true
            }
          ], 
          "key": "LProp3d_SurfaceTool::D1(opencascade::handle<Adaptor3d_HSurface>, Standard_Real, Standard_Real, gp_Pnt, gp_Vec, gp_Vec)", 
          "returnType": "void", 
          "static": "1", 
          "throws": true
        }, 
        {
          "declType": "method", 
          "name": "D2", 
          "parent": "LProp3d_SurfaceTool", 
          "arguments": [
            {
              "type": "opencascade::handle<Adaptor3d_HSurface>", 
              "name": "S", 
              "const": true, 
              "ref": true
            }, 
            {
              "type": "Standard_Real", 
              "name": "U", 
              "const": true
            }, 
            {
              "type": "Standard_Real", 
              "name": "V", 
              "const": true
            }, 
            {
              "type": "gp_Pnt", 
              "name": "P", 
              "ref": true
            }, 
            {
              "type": "gp_Vec", 
              "name": "D1U", 
              "ref": true
            }, 
            {
              "type": "gp_Vec", 
              "name": "D1V", 
              "ref": true
            }, 
            {
              "type": "gp_Vec", 
              "name": "D2U", 
              "ref": true
            }, 
            {
              "type": "gp_Vec", 
              "name": "D2V", 
              "ref": true
            }, 
            {
              "type": "gp_Vec", 
              "name": "DUV", 
              "ref": true
            }
          ], 
          "key": "LProp3d_SurfaceTool::D2(opencascade::handle<Adaptor3d_HSurface>, Standard_Real, Standard_Real, gp_Pnt, gp_Vec, gp_Vec, gp_Vec, gp_Vec, gp_Vec)", 
          "returnType": "void", 
          "static": "1", 
          "throws": true
        }, 
        {
          "declType": "method", 
          "name": "DN", 
          "parent": "LProp3d_SurfaceTool", 
          "arguments": [
            {
              "type": "opencascade::handle<Adaptor3d_HSurface>", 
              "name": "S", 
              "const": true, 
              "ref": true
            }, 
            {
              "type": "Standard_Real", 
              "name": "U", 
              "const": true
            }, 
            {
              "type": "Standard_Real", 
              "name": "V", 
              "const": true
            }, 
            {
              "type": "Standard_Integer", 
              "name": "IU", 
              "const": true
            }, 
            {
              "type": "Standard_Integer", 
              "name": "IV", 
              "const": true
            }
          ], 
          "key": "LProp3d_SurfaceTool::DN(opencascade::handle<Adaptor3d_HSurface>, Standard_Real, Standard_Real, Standard_Integer, Standard_Integer)", 
          "returnType": "gp_Vec", 
          "static": "1", 
          "throws": true
        }, 
        {
          "declType": "method", 
          "name": "Continuity", 
          "parent": "LProp3d_SurfaceTool", 
          "arguments": [
            {
              "type": "opencascade::handle<Adaptor3d_HSurface>", 
              "name": "S", 
              "const": true, 
              "ref": true
            }
          ], 
          "key": "LProp3d_SurfaceTool::Continuity(opencascade::handle<Adaptor3d_HSurface>)", 
          "returnType": "Standard_Integer", 
          "static": "1", 
          "throws": true
        }, 
        {
          "declType": "method", 
          "name": "Bounds", 
          "parent": "LProp3d_SurfaceTool", 
          "arguments": [
            {
              "type": "opencascade::handle<Adaptor3d_HSurface>", 
              "name": "S", 
              "const": true, 
              "ref": true
            }, 
            {
              "type": "Standard_Real", 
              "name": "U1", 
              "ref": true
            }, 
            {
              "type": "Standard_Real", 
              "name": "V1", 
              "ref": true
            }, 
            {
              "type": "Standard_Real", 
              "name": "U2", 
              "ref": true
            }, 
            {
              "type": "Standard_Real", 
              "name": "V2", 
              "ref": true
            }
          ], 
          "key": "LProp3d_SurfaceTool::Bounds(opencascade::handle<Adaptor3d_HSurface>, Standard_Real, Standard_Real, Standard_Real, Standard_Real)", 
          "returnType": "void", 
          "static": "1", 
          "throws": true
        }
      ], 
      "artificial": false, 
      "bases": [], 
      "location": [
        "/usr/local/include/opencascade/LProp3d_SurfaceTool.hxx", 
        31
      ], 
      "key": "LProp3d_SurfaceTool"
    }, 
    {
      "declType": "class", 
      "name": "LProp3d_SLProps", 
      "abstract": false, 
      "declarations": [
        {
          "declType": "method", 
          "name": "LProp3d_SLProps", 
          "parent": "LProp3d_SLProps", 
          "arguments": [
            {
              "type": "opencascade::handle<Adaptor3d_HSurface>", 
              "name": "S", 
              "const": true, 
              "ref": true
            }, 
            {
              "type": "Standard_Real", 
              "name": "U", 
              "const": true
            }, 
            {
              "type": "Standard_Real", 
              "name": "V", 
              "const": true
            }, 
            {
              "type": "Standard_Integer", 
              "name": "N", 
              "const": true
            }, 
            {
              "type": "Standard_Real", 
              "name": "Resolution", 
              "const": true
            }
          ], 
          "key": "LProp3d_SLProps::LProp3d_SLProps(opencascade::handle<Adaptor3d_HSurface>, Standard_Real, Standard_Real, Standard_Integer, Standard_Real)", 
          "returnType": "", 
          "throws": true, 
          "type": "constructor"
        }, 
        {
          "declType": "method", 
          "name": "LProp3d_SLProps", 
          "parent": "LProp3d_SLProps", 
          "arguments": [
            {
              "type": "opencascade::handle<Adaptor3d_HSurface>", 
              "name": "S", 
              "const": true, 
              "ref": true
            }, 
            {
              "type": "Standard_Integer", 
              "name": "N", 
              "const": true
            }, 
            {
              "type": "Standard_Real", 
              "name": "Resolution", 
              "const": true
            }
          ], 
          "key": "LProp3d_SLProps::LProp3d_SLProps(opencascade::handle<Adaptor3d_HSurface>, Standard_Integer, Standard_Real)", 
          "returnType": "", 
          "throws": true, 
          "type": "constructor"
        }, 
        {
          "declType": "method", 
          "name": "LProp3d_SLProps", 
          "parent": "LProp3d_SLProps", 
          "arguments": [
            {
              "type": "Standard_Integer", 
              "name": "N", 
              "const": true
            }, 
            {
              "type": "Standard_Real", 
              "name": "Resolution", 
              "const": true
            }
          ], 
          "key": "LProp3d_SLProps::LProp3d_SLProps(Standard_Integer, Standard_Real)", 
          "returnType": "", 
          "throws": true, 
          "type": "constructor"
        }, 
        {
          "declType": "method", 
          "name": "LProp3d_SLProps", 
          "parent": "LProp3d_SLProps", 
          "arguments": [
            {
              "type": "LProp3d_SLProps", 
              "name": "arg0", 
              "const": true, 
              "ref": true
            }
          ], 
          "key": "LProp3d_SLProps::LProp3d_SLProps(LProp3d_SLProps)", 
          "returnType": "", 
          "artificial": "1", 
          "throws": true, 
          "type": "constructor", 
          "copyConstructor": true
        }, 
        {
          "declType": "method", 
          "name": "SetSurface", 
          "parent": "LProp3d_SLProps", 
          "arguments": [
            {
              "type": "opencascade::handle<Adaptor3d_HSurface>", 
              "name": "S", 
              "const": true, 
              "ref": true
            }
          ], 
          "key": "LProp3d_SLProps::SetSurface(opencascade::handle<Adaptor3d_HSurface>)", 
          "returnType": "void", 
          "throws": true
        }, 
        {
          "declType": "method", 
          "name": "SetParameters", 
          "parent": "LProp3d_SLProps", 
          "arguments": [
            {
              "type": "Standard_Real", 
              "name": "U", 
              "const": true
            }, 
            {
              "type": "Standard_Real", 
              "name": "V", 
              "const": true
            }
          ], 
          "key": "LProp3d_SLProps::SetParameters(Standard_Real, Standard_Real)", 
          "returnType": "void", 
          "throws": true
        }, 
        {
          "declType": "method", 
          "name": "Value", 
          "parent": "LProp3d_SLProps", 
          "arguments": [], 
          "key": "LProp3d_SLProps::Value()", 
          "returnType": "gp_Pnt const &", 
          "const": "1", 
          "throws": true
        }, 
        {
          "declType": "method", 
          "name": "D1U", 
          "parent": "LProp3d_SLProps", 
          "arguments": [], 
          "key": "LProp3d_SLProps::D1U()", 
          "returnType": "gp_Vec const &", 
          "throws": true
        }, 
        {
          "declType": "method", 
          "name": "D1V", 
          "parent": "LProp3d_SLProps", 
          "arguments": [], 
          "key": "LProp3d_SLProps::D1V()", 
          "returnType": "gp_Vec const &", 
          "throws": true
        }, 
        {
          "declType": "method", 
          "name": "D2U", 
          "parent": "LProp3d_SLProps", 
          "arguments": [], 
          "key": "LProp3d_SLProps::D2U()", 
          "returnType": "gp_Vec const &", 
          "throws": true
        }, 
        {
          "declType": "method", 
          "name": "D2V", 
          "parent": "LProp3d_SLProps", 
          "arguments": [], 
          "key": "LProp3d_SLProps::D2V()", 
          "returnType": "gp_Vec const &", 
          "throws": true
        }, 
        {
          "declType": "method", 
          "name": "DUV", 
          "parent": "LProp3d_SLProps", 
          "arguments": [], 
          "key": "LProp3d_SLProps::DUV()", 
          "returnType": "gp_Vec const &", 
          "throws": true
        }, 
        {
          "declType": "method", 
          "name": "IsTangentUDefined", 
          "parent": "LProp3d_SLProps", 
          "arguments": [], 
          "key": "LProp3d_SLProps::IsTangentUDefined()", 
          "returnType": "Standard_Boolean", 
          "throws": true
        }, 
        {
          "declType": "method", 
          "name": "TangentU", 
          "parent": "LProp3d_SLProps", 
          "arguments": [
            {
              "type": "gp_Dir", 
              "name": "D", 
              "ref": true
            }
          ], 
          "key": "LProp3d_SLProps::TangentU(gp_Dir)", 
          "returnType": "void", 
          "throws": true
        }, 
        {
          "declType": "method", 
          "name": "IsTangentVDefined", 
          "parent": "LProp3d_SLProps", 
          "arguments": [], 
          "key": "LProp3d_SLProps::IsTangentVDefined()", 
          "returnType": "Standard_Boolean", 
          "throws": true
        }, 
        {
          "declType": "method", 
          "name": "TangentV", 
          "parent": "LProp3d_SLProps", 
          "arguments": [
            {
              "type": "gp_Dir", 
              "name": "D", 
              "ref": true
            }
          ], 
          "key": "LProp3d_SLProps::TangentV(gp_Dir)", 
          "returnType": "void", 
          "throws": true
        }, 
        {
          "declType": "method", 
          "name": "IsNormalDefined", 
          "parent": "LProp3d_SLProps", 
          "arguments": [], 
          "key": "LProp3d_SLProps::IsNormalDefined()", 
          "returnType": "Standard_Boolean", 
          "throws": true
        }, 
        {
          "declType": "method", 
          "name": "Normal", 
          "parent": "LProp3d_SLProps", 
          "arguments": [], 
          "key": "LProp3d_SLProps::Normal()", 
          "returnType": "gp_Dir const &", 
          "throws": true
        }, 
        {
          "declType": "method", 
          "name": "IsCurvatureDefined", 
          "parent": "LProp3d_SLProps", 
          "arguments": [], 
          "key": "LProp3d_SLProps::IsCurvatureDefined()", 
          "returnType": "Standard_Boolean", 
          "throws": true
        }, 
        {
          "declType": "method", 
          "name": "IsUmbilic", 
          "parent": "LProp3d_SLProps", 
          "arguments": [], 
          "key": "LProp3d_SLProps::IsUmbilic()", 
          "returnType": "Standard_Boolean", 
          "throws": true
        }, 
        {
          "declType": "method", 
          "name": "MaxCurvature", 
          "parent": "LProp3d_SLProps", 
          "arguments": [], 
          "key": "LProp3d_SLProps::MaxCurvature()", 
          "returnType": "Standard_Real", 
          "throws": true
        }, 
        {
          "declType": "method", 
          "name": "MinCurvature", 
          "parent": "LProp3d_SLProps", 
          "arguments": [], 
          "key": "LProp3d_SLProps::MinCurvature()", 
          "returnType": "Standard_Real", 
          "throws": true
        }, 
        {
          "declType": "method", 
          "name": "CurvatureDirections", 
          "parent": "LProp3d_SLProps", 
          "arguments": [
            {
              "type": "gp_Dir", 
              "name": "MaxD", 
              "ref": true
            }, 
            {
              "type": "gp_Dir", 
              "name": "MinD", 
              "ref": true
            }
          ], 
          "key": "LProp3d_SLProps::CurvatureDirections(gp_Dir, gp_Dir)", 
          "returnType": "void", 
          "throws": true
        }, 
        {
          "declType": "method", 
          "name": "MeanCurvature", 
          "parent": "LProp3d_SLProps", 
          "arguments": [], 
          "key": "LProp3d_SLProps::MeanCurvature()", 
          "returnType": "Standard_Real", 
          "throws": true
        }, 
        {
          "declType": "method", 
          "name": "GaussianCurvature", 
          "parent": "LProp3d_SLProps", 
          "arguments": [], 
          "key": "LProp3d_SLProps::GaussianCurvature()", 
          "returnType": "Standard_Real", 
          "throws": true
        }
      ], 
      "artificial": false, 
      "bases": [], 
      "location": [
        "/usr/local/include/opencascade/LProp3d_SLProps.hxx", 
        42
      ], 
      "key": "LProp3d_SLProps"
    }
  ], 
  "name": "LProp3d"
}